django_secrecy/__init__.py
django_secrecy/apps.py
django_secrecy/generator.py
django_secrecy/main.py
django_secrecy/test.py
django_secrecy/utils.py
django_secrecy/management/__init__.py
django_secrecy/management/commands/__init__.py
django_secrecy/management/commands/secrecy.py
django_secrecy/tpl/__init__.py
django_secrecy/tpl/base_tpl.py
django_secrecy/tpl/development_tpl.py
django_secrecy/tpl/init_tpl.py
django_secrecy/tpl/production_tpl.py
django_secrecy-0.99.5.dist-info/LICENSE
django_secrecy-0.99.5.dist-info/METADATA
django_secrecy-0.99.5.dist-info/WHEEL
django_secrecy-0.99.5.dist-info/entry_points.txt
django_secrecy-0.99.5.dist-info/top_level.txt
django_secrecy-0.99.5.dist-info/RECORD
