Metadata-Version: 2.1
Name: django-secrecy
Version: 0.99.5
Summary: Django secret project variables
Home-page: https://github.com/Cyxapic/django-secrecy
Author: Artem Sukharenko
Author-email: truecyxapic@yandex.ru
License: MIT
Keywords: SECRET_KEY,Project settings
Platform: UNKNOWN
Classifier: Development Status :: 3 - Alpha
Classifier: Intended Audience :: Developers
Classifier: Topic :: Software Development :: Build Tools
Classifier: License :: OSI Approved :: MIT License
Classifier: Programming Language :: Python :: 3.6
